apikit/__init__.py
apikit/api_collection.py
apikit/client.py
apikit/envvar.py
apikit/schema.py
pyapikit-1.0.0.dist-info/METADATA
pyapikit-1.0.0.dist-info/WHEEL
pyapikit-1.0.0.dist-info/top_level.txt
pyapikit-1.0.0.dist-info/RECORD
